oarepo_oaipmh_harvester/__init__.py
oarepo_oaipmh_harvester/cli.py
oarepo_oaipmh_harvester/components.py
oarepo_oaipmh_harvester/config.py
oarepo_oaipmh_harvester/ext.py
oarepo_oaipmh_harvester/harvester.py
oarepo_oaipmh_harvester/models.py
oarepo_oaipmh_harvester/permissions.py
oarepo_oaipmh_harvester/proxies.py
oarepo_oaipmh_harvester/reader_callback.py
oarepo_oaipmh_harvester/tasks.py
oarepo_oaipmh_harvester/uow.py
oarepo_oaipmh_harvester/utils.py
oarepo_oaipmh_harvester/administration/__init__.py
oarepo_oaipmh_harvester/administration/base.py
oarepo_oaipmh_harvester/administration/harvester/__init__.py
oarepo_oaipmh_harvester/administration/harvester/api.py
oarepo_oaipmh_harvester/administration/harvester/views.py
oarepo_oaipmh_harvester/administration/record/__init__.py
oarepo_oaipmh_harvester/administration/record/api.py
oarepo_oaipmh_harvester/administration/record/views.py
oarepo_oaipmh_harvester/administration/run/__init__.py
oarepo_oaipmh_harvester/administration/run/api.py
oarepo_oaipmh_harvester/administration/run/views.py
oarepo_oaipmh_harvester/administration/views/__init__.py
oarepo_oaipmh_harvester/administration/views/record.py
oarepo_oaipmh_harvester/administration/views/run.py
oarepo_oaipmh_harvester/alembic/5f7f68fc9fe4_create_run_and_record_tables.py
oarepo_oaipmh_harvester/alembic/__init__.py
oarepo_oaipmh_harvester/alembic/b2a45c3a744e_initial_revision.py
oarepo_oaipmh_harvester/alembic/cecc281d2938_create_oarepo_oaipmh_harvester_branch.py
oarepo_oaipmh_harvester/common/__init__.py
oarepo_oaipmh_harvester/common/records/__init__.py
oarepo_oaipmh_harvester/common/records/oai_harvester.py
oarepo_oaipmh_harvester/common/resources/__init__.py
oarepo_oaipmh_harvester/common/resources/records/__init__.py
oarepo_oaipmh_harvester/common/resources/records/harvester_config.py
oarepo_oaipmh_harvester/common/resources/records/harvester_resource.py
oarepo_oaipmh_harvester/common/services/__init__.py
oarepo_oaipmh_harvester/common/services/oai_harvester.py
oarepo_oai_pmh_harvester-5.0.11.dist-info/METADATA
oarepo_oai_pmh_harvester-5.0.11.dist-info/WHEEL
oarepo_oai_pmh_harvester-5.0.11.dist-info/entry_points.txt
oarepo_oai_pmh_harvester-5.0.11.dist-info/top_level.txt
oarepo_oai_pmh_harvester-5.0.11.dist-info/RECORD
