Metadata-Version: 2.4
Name: oarepo-oai-pmh-harvester
Version: 5.0.11
Summary: OAIPMH harvester
Requires-Dist: tqdm>=4.64.1
Requires-Dist: oarepo-runtime>=1.4.44
Requires-Dist: oarepo-ui>=5.0.89
Requires-Dist: sickle
Requires-Dist: pyyaml
Requires-Dist: oarepo-runtime>=1.0.0
Requires-Dist: oarepo-global-search>=1.0.23
Requires-Dist: deepmerge>=1.1.0
Requires-Dist: oarepo-vocabularies>=2.0.0
Requires-Dist: oarepo-requests>=1.0.2
Requires-Dist: oarepo-communities>=5.0.0
Requires-Dist: oarepo-global-search>=1.0.20
Requires-Dist: oarepo-workflows>=1.0.0
Provides-Extra: tests
Requires-Dist: pytest-invenio[opensearch2]; extra == "tests"
Requires-Dist: black; extra == "tests"
Requires-Dist: isort; extra == "tests"
Requires-Dist: autoflake; extra == "tests"
Requires-Dist: pytest-invenio>=1.4.11; extra == "tests"
Provides-Extra: dev
Requires-Dist: oarepo-tools; extra == "dev"
